genomic_references/__init__.py
genomic_references/__version__.py
genomic_references/annotation.py
genomic_references/base_dir.py
genomic_references/genomic_reference.py
genomic_references/helpers.py
genomic_references-1.1.0.dist-info/WHEEL
genomic_references-1.1.0.dist-info/METADATA
genomic_references-1.1.0.dist-info/RECORD
